[
  { "carName": "Volkswagen" },
  { "carName": "GMC" },
  { "carName": "Mazda" },
  { "carName": "Mercury" },
  { "carName": "BMW" },
  { "carName": "Lexus" },
  { "carName": "Ford" },
  { "carName": "Pontiac" },
  { "carName": "Mitsubishi" },
  { "carName": "Hyundai" },
  { "carName": "Ford" },
  { "carName": "Mazda" },
  { "carName": "Volkswagen" },
  { "carName": "Subaru" },
  { "carName": "Chevrolet" },
  { "carName": "Volvo" },
  { "carName": "Land Rover" },
  { "carName": "Toyota" },
  { "carName": "Honda" },
  { "carName": "Pontiac" },
  { "carName": "Lotus" },
  { "carName": "Chrysler" },
  { "carName": "Cadillac" },
  { "carName": "Isuzu" },
  { "carName": "Subaru" },
  { "carName": "Ford" },
  { "carName": "Volkswagen" },
  { "carName": "Pontiac" },
  { "carName": "Dodge" },
  { "carName": "Dodge" },
  { "carName": "Mercedes-Benz" },
  { "carName": "Mitsubishi" },
  { "carName": "Mitsubishi" },
  { "carName": "Pontiac" },
  { "carName": "Chevrolet" },
  { "carName": "Oldsmobile" },
  { "carName": "Honda" },
  { "carName": "Jaguar" },
  { "carName": "Saturn" },
  { "carName": "Mitsubishi" },
  { "carName": "Toyota" },
  { "carName": "Aston Martin" },
  { "carName": "Hummer" },
  { "carName": "Honda" },
  { "carName": "Ford" },
  { "carName": "Buick" },
  { "carName": "Buick" },
  { "carName": "GMC" },
  { "carName": "BMW" },
  { "carName": "Ford" },
  { "carName": "Porsche" },
  { "carName": "Infiniti" },
  { "carName": "Buick" },
  { "carName": "Nissan" },
  { "carName": "Buick" },
  { "carName": "Hyundai" },
  { "carName": "Infiniti" },
  { "carName": "Honda" },
  { "carName": "Lamborghini" },
  { "carName": "Ford" },
  { "carName": "Nissan" },
  { "carName": "Volvo" },
  { "carName": "Porsche" },
  { "carName": "Toyota" },
  { "carName": "Buick" },
  { "carName": "Saab" },
  { "carName": "Dodge" },
  { "carName": "Toyota" },
  { "carName": "Jaguar" },
  { "carName": "Mitsubishi" },
  { "carName": "Honda" },
  { "carName": "Ford" },
  { "carName": "Infiniti" },
  { "carName": "Ford" },
  { "carName": "Mazda" },
  { "carName": "Honda" },
  { "carName": "Ford" },
  { "carName": "BMW" },
  { "carName": "Ford" },
  { "carName": "Audi" },
  { "carName": "Chevrolet" },
  { "carName": "Chevrolet" },
  { "carName": "BMW" },
  { "carName": "GMC" },
  { "carName": "Land Rover" },
  { "carName": "Mitsubishi" },
  { "carName": "Ford" },
  { "carName": "Mercedes-Benz" },
  { "carName": "Mercedes-Benz" },
  { "carName": "Hummer" },
  { "carName": "Pontiac" },
  { "carName": "Pontiac" },
  { "carName": "Chrysler" },
  { "carName": "Toyota" },
  { "carName": "Mercedes-Benz" },
  { "carName": "Lexus" },
  { "carName": "Land Rover" },
  { "carName": "Toyota" },
  { "carName": "Lotus" },
  { "carName": "Hyundai" },
  { "carName": "Audi" },
  { "carName": "Dodge" },
  { "carName": "Pontiac" },
  { "carName": "Ford" },
  { "carName": "Nissan" },
  { "carName": "Cadillac" },
  { "carName": "Land Rover" },
  { "carName": "Mitsubishi" },
  { "carName": "Plymouth" },
  { "carName": "Dodge" },
  { "carName": "Jeep" },
  { "carName": "Audi" },
  { "carName": "Pontiac" },
  { "carName": "Honda" },
  { "carName": "Pontiac" },
  { "carName": "GMC" },
  { "carName": "Chevrolet" },
  { "carName": "Isuzu" },
  { "carName": "Oldsmobile" },
  { "carName": "Chevrolet" },
  { "carName": "Dodge" },
  { "carName": "Acura" },
  { "carName": "Hyundai" },
  { "carName": "Ford" },
  { "carName": "Lexus" },
  { "carName": "GMC" },
  { "carName": "Chrysler" },
  { "carName": "Dodge" },
  { "carName": "Ford" },
  { "carName": "Pontiac" },
  { "carName": "Lexus" },
  { "carName": "Jeep" },
  { "carName": "Ford" },
  { "carName": "Chevrolet" },
  { "carName": "Audi" },
  { "carName": "Hyundai" },
  { "carName": "GMC" },
  { "carName": "Bentley" },
  { "carName": "Audi" },
  { "carName": "Honda" },
  { "carName": "Lincoln" },
  { "carName": "Dodge" },
  { "carName": "Infiniti" },
  { "carName": "Lexus" },
  { "carName": "Dodge" },
  { "carName": "Chevrolet" },
  { "carName": "Subaru" },
  { "carName": "Pontiac" },
  { "carName": "Hyundai" },
  { "carName": "Mazda" },
  { "carName": "Toyota" },
  { "carName": "Pontiac" },
  { "carName": "Cadillac" },
  { "carName": "Porsche" },
  { "carName": "Scion" },
  { "carName": "Buick" },
  { "carName": "Honda" },
  { "carName": "Chevrolet" },
  { "carName": "Mercedes-Benz" },
  { "carName": "Toyota" },
  { "carName": "Toyota" },
  { "carName": "Chevrolet" },
  { "carName": "Porsche" },
  { "carName": "Oldsmobile" },
  { "carName": "Dodge" },
  { "carName": "Jeep" },
  { "carName": "Lotus" },
  { "carName": "Volkswagen" },
  { "carName": "Cadillac" },
  { "carName": "Isuzu" },
  { "carName": "Dodge" },
  { "carName": "Kia" },
  { "carName": "Volvo" },
  { "carName": "Buick" },
  { "carName": "Chevrolet" },
  { "carName": "GMC" },
  { "carName": "Geo" },
  { "carName": "Buick" },
  { "carName": "Toyota" },
  { "carName": "Ford" },
  { "carName": "Mercury" },
  { "carName": "Ford" },
  { "carName": "GMC" },
  { "carName": "Bentley" },
  { "carName": "Pontiac" },
  { "carName": "Maybach" },
  { "carName": "Mercedes-Benz" },
  { "carName": "Mercury" },
  { "carName": "Jaguar" },
  { "carName": "Dodge" },
  { "carName": "Chrysler" },
  { "carName": "Mercury" },
  { "carName": "Chevrolet" },
  { "carName": "Plymouth" },
  { "carName": "Chevrolet" },
  { "carName": "Nissan" },
  { "carName": "Chevrolet" },
  { "carName": "Suzuki" },
  { "carName": "Isuzu" },
  { "carName": "Mitsubishi" },
  { "carName": "Dodge" },
  { "carName": "Hyundai" },
  { "carName": "Ford" },
  { "carName": "Mazda" },
  { "carName": "Chevrolet" },
  { "carName": "Ford" },
  { "carName": "GMC" },
  { "carName": "Mitsubishi" },
  { "carName": "Kia" },
  { "carName": "Ford" },
  { "carName": "Mitsubishi" },
  { "carName": "Lexus" },
  { "carName": "Pontiac" },
  { "carName": "Cadillac" },
  { "carName": "Volkswagen" },
  { "carName": "Mitsubishi" },
  { "carName": "Isuzu" },
  { "carName": "GMC" },
  { "carName": "Audi" },
  { "carName": "Nissan" },
  { "carName": "Maserati" },
  { "carName": "Mazda" },
  { "carName": "Audi" },
  { "carName": "Ford" },
  { "carName": "Toyota" },
  { "carName": "GMC" },
  { "carName": "Lotus" },
  { "carName": "GMC" },
  { "carName": "Toyota" },
  { "carName": "Plymouth" },
  { "carName": "Chevrolet" },
  { "carName": "Pontiac" },
  { "carName": "Lincoln" },
  { "carName": "Mitsubishi" },
  { "carName": "Porsche" },
  { "carName": "Kia" },
  { "carName": "BMW" },
  { "carName": "Porsche" },
  { "carName": "GMC" },
  { "carName": "Ford" },
  { "carName": "Toyota" },
  { "carName": "Nissan" },
  { "carName": "Cadillac" },
  { "carName": "Acura" },
  { "carName": "Lincoln" },
  { "carName": "Mazda" },
  { "carName": "Jeep" },
  { "carName": "Buick" },
  { "carName": "Suzuki" },
  { "carName": "Mitsubishi" },
  { "carName": "Chevrolet" },
  { "carName": "Chevrolet" },
  { "carName": "Volkswagen" },
  { "carName": "Honda" },
  { "carName": "Dodge" },
  { "carName": "Toyota" },
  { "carName": "Lexus" },
  { "carName": "Infiniti" },
  { "carName": "Dodge" },
  { "carName": "GMC" },
  { "carName": "BMW" },
  { "carName": "Eagle" },
  { "carName": "BMW" },
  { "carName": "Mazda" },
  { "carName": "Mazda" },
  { "carName": "Chrysler" },
  { "carName": "Ford" },
  { "carName": "Maserati" },
  { "carName": "Buick" },
  { "carName": "Ford" },
  { "carName": "Lexus" },
  { "carName": "BMW" },
  { "carName": "Volkswagen" },
  { "carName": "Subaru" },
  { "carName": "Infiniti" },
  { "carName": "Chevrolet" },
  { "carName": "BMW" },
  { "carName": "Ford" },
  { "carName": "Lincoln" },
  { "carName": "Geo" },
  { "carName": "Cadillac" },
  { "carName": "Audi" },
  { "carName": "Panoz" },
  { "carName": "Mazda" },
  { "carName": "Buick" },
  { "carName": "Cadillac" },
  { "carName": "BMW" },
  { "carName": "Volvo" },
  { "carName": "Subaru" },
  { "carName": "Ford" },
  { "carName": "Oldsmobile" },
  { "carName": "Ford" },
  { "carName": "GMC" },
  { "carName": "Chevrolet" },
  { "carName": "Dodge" },
  { "carName": "Chevrolet" },
  { "carName": "GMC" },
  { "carName": "BMW" },
  { "carName": "Land Rover" },
  { "carName": "Ford" },
  { "carName": "Hyundai" },
  { "carName": "Nissan" },
  { "carName": "Ford" },
  { "carName": "Volvo" },
  { "carName": "Mazda" },
  { "carName": "Chevrolet" },
  { "carName": "Pontiac" },
  { "carName": "Audi" },
  { "carName": "Dodge" },
  { "carName": "Audi" },
  { "carName": "Mitsubishi" },
  { "carName": "Nissan" },
  { "carName": "Mitsubishi" },
  { "carName": "Cadillac" },
  { "carName": "Mercedes-Benz" },
  { "carName": "Oldsmobile" },
  { "carName": "Mercedes-Benz" },
  { "carName": "Buick" },
  { "carName": "Dodge" },
  { "carName": "Dodge" },
  { "carName": "Dodge" },
  { "carName": "Mazda" },
  { "carName": "Bentley" },
  { "carName": "Mazda" },
  { "carName": "Mercury" },
  { "carName": "Chrysler" },
  { "carName": "GMC" },
  { "carName": "MINI" },
  { "carName": "Cadillac" },
  { "carName": "Mazda" },
  { "carName": "Hyundai" },
  { "carName": "Audi" },
  { "carName": "Chevrolet" },
  { "carName": "Chevrolet" },
  { "carName": "Chrysler" },
  { "carName": "GMC" },
  { "carName": "Chevrolet" },
  { "carName": "Cadillac" },
  { "carName": "Lexus" },
  { "carName": "Dodge" },
  { "carName": "Kia" },
  { "carName": "Saturn" },
  { "carName": "Subaru" },
  { "carName": "Nissan" },
  { "carName": "Bentley" },
  { "carName": "Toyota" },
  { "carName": "GMC" },
  { "carName": "Toyota" },
  { "carName": "Audi" },
  { "carName": "Volvo" },
  { "carName": "Kia" },
  { "carName": "Honda" },
  { "carName": "Ford" },
  { "carName": "Lexus" },
  { "carName": "Ford" },
  { "carName": "GMC" },
  { "carName": "GMC" },
  { "carName": "Chevrolet" },
  { "carName": "Pontiac" },
  { "carName": "Chevrolet" },
  { "carName": "Audi" },
  { "carName": "GMC" },
  { "carName": "Lexus" },
  { "carName": "Audi" },
  { "carName": "Audi" },
  { "carName": "Subaru" },
  { "carName": "Honda" },
  { "carName": "Mazda" },
  { "carName": "Hummer" },
  { "carName": "Ford" },
  { "carName": "Acura" },
  { "carName": "Plymouth" },
  { "carName": "Mercedes-Benz" },
  { "carName": "Chevrolet" },
  { "carName": "Lexus" },
  { "carName": "Ford" },
  { "carName": "Land Rover" },
  { "carName": "Ford" },
  { "carName": "MINI" },
  { "carName": "Mazda" },
  { "carName": "Chrysler" },
  { "carName": "Mercedes-Benz" },
  { "carName": "Isuzu" },
  { "carName": "GMC" },
  { "carName": "Mitsubishi" },
  { "carName": "Lincoln" },
  { "carName": "Acura" },
  { "carName": "BMW" },
  { "carName": "Mazda" },
  { "carName": "Volvo" },
  { "carName": "Mazda" },
  { "carName": "Mercury" },
  { "carName": "Land Rover" },
  { "carName": "Buick" },
  { "carName": "Ford" },
  { "carName": "Toyota" },
  { "carName": "Dodge" },
  { "carName": "Chevrolet" },
  { "carName": "Geo" },
  { "carName": "Nissan" },
  { "carName": "Dodge" },
  { "carName": "Porsche" },
  { "carName": "Rolls-Royce" },
  { "carName": "Mercedes-Benz" },
  { "carName": "Mazda" },
  { "carName": "Volkswagen" },
  { "carName": "Audi" },
  { "carName": "Honda" },
  { "carName": "Rolls-Royce" },
  { "carName": "Subaru" },
  { "carName": "Mazda" },
  { "carName": "Cadillac" },
  { "carName": "Lamborghini" },
  { "carName": "Dodge" },
  { "carName": "Dodge" },
  { "carName": "Ford" },
  { "carName": "Kia" },
  { "carName": "GMC" },
  { "carName": "Buick" },
  { "carName": "Toyota" },
  { "carName": "Acura" },
  { "carName": "Dodge" },
  { "carName": "Ford" },
  { "carName": "Hummer" },
  { "carName": "Chevrolet" },
  { "carName": "Dodge" },
  { "carName": "Lotus" },
  { "carName": "Mazda" },
  { "carName": "Acura" },
  { "carName": "Chevrolet" },
  { "carName": "Honda" },
  { "carName": "Volkswagen" },
  { "carName": "Pontiac" },
  { "carName": "Toyota" },
  { "carName": "Pontiac" },
  { "carName": "Mitsubishi" },
  { "carName": "Ford" },
  { "carName": "Mercedes-Benz" },
  { "carName": "Honda" },
  { "carName": "Lamborghini" },
  { "carName": "Volvo" },
  { "carName": "Hyundai" },
  { "carName": "Chrysler" },
  { "carName": "Ford" },
  { "carName": "Volkswagen" },
  { "carName": "Ford" },
  { "carName": "GMC" },
  { "carName": "Mercedes-Benz" },
  { "carName": "Honda" },
  { "carName": "Chevrolet" },
  { "carName": "BMW" },
  { "carName": "Ford" },
  { "carName": "Ford" },
  { "carName": "GMC" },
  { "carName": "Dodge" },
  { "carName": "Mazda" },
  { "carName": "Mercury" },
  { "carName": "Pontiac" },
  { "carName": "BMW" },
  { "carName": "Dodge" },
  { "carName": "Mitsubishi" },
  { "carName": "Mazda" },
  { "carName": "Dodge" },
  { "carName": "Mercedes-Benz" },
  { "carName": "Nissan" },
  { "carName": "Ford" },
  { "carName": "BMW" },
  { "carName": "Cadillac" },
  { "carName": "Toyota" },
  { "carName": "Dodge" },
  { "carName": "Suzuki" },
  { "carName": "Chevrolet" },
  { "carName": "MINI" },
  { "carName": "Ford" },
  { "carName": "Buick" },
  { "carName": "Jaguar" },
  { "carName": "Aston Martin" },
  { "carName": "Ford" },
  { "carName": "Ford" },
  { "carName": "Nissan" },
  { "carName": "Mercedes-Benz" },
  { "carName": "Acura" },
  { "carName": "Plymouth" },
  { "carName": "Volvo" },
  { "carName": "Acura" },
  { "carName": "Acura" },
  { "carName": "Toyota" },
  { "carName": "Ford" },
  { "carName": "Saab" },
  { "carName": "Isuzu" },
  { "carName": "Volkswagen" },
  { "carName": "Mercury" },
  { "carName": "Bentley" },
  { "carName": "GMC" },
  { "carName": "Volkswagen" },
  { "carName": "Pontiac" },
  { "carName": "Suzuki" },
  { "carName": "GMC" },
  { "carName": "Chevrolet" },
  { "carName": "GMC" },
  { "carName": "Ford" },
  { "carName": "Buick" },
  { "carName": "Toyota" },
  { "carName": "MINI" },
  { "carName": "Audi" },
  { "carName": "Land Rover" },
  { "carName": "Chevrolet" },
  { "carName": "Chrysler" },
  { "carName": "Kia" },
  { "carName": "Mercury" },
  { "carName": "Lincoln" },
  { "carName": "Nissan" },
  { "carName": "Chevrolet" },
  { "carName": "Mitsubishi" },
  { "carName": "Cadillac" },
  { "carName": "GMC" },
  { "carName": "Acura" },
  { "carName": "Dodge" },
  { "carName": "Ford" },
  { "carName": "Chevrolet" },
  { "carName": "Honda" },
  { "carName": "Nissan" },
  { "carName": "Lincoln" },
  { "carName": "Toyota" },
  { "carName": "Pontiac" },
  { "carName": "Ford" },
  { "carName": "Lexus" },
  { "carName": "Mercury" },
  { "carName": "Maybach" },
  { "carName": "Mitsubishi" },
  { "carName": "Buick" },
  { "carName": "Mercury" },
  { "carName": "Chevrolet" },
  { "carName": "Chevrolet" },
  { "carName": "Mercury" },
  { "carName": "Plymouth" },
  { "carName": "Cadillac" },
  { "carName": "Lexus" },
  { "carName": "Cadillac" },
  { "carName": "Mercedes-Benz" },
  { "carName": "Ford" },
  { "carName": "Oldsmobile" },
  { "carName": "GMC" },
  { "carName": "Mitsubishi" },
  { "carName": "Mitsubishi" },
  { "carName": "Land Rover" },
  { "carName": "Mercedes-Benz" },
  { "carName": "Mitsubishi" },
  { "carName": "Lincoln" },
  { "carName": "Ford" },
  { "carName": "Mercury" },
  { "carName": "GMC" },
  { "carName": "Chevrolet" },
  { "carName": "Volkswagen" },
  { "carName": "Toyota" },
  { "carName": "Dodge" },
  { "carName": "Toyota" },
  { "carName": "Saturn" },
  { "carName": "Pontiac" },
  { "carName": "BMW" },
  { "carName": "Mercury" },
  { "carName": "Volvo" },
  { "carName": "Suzuki" },
  { "carName": "Acura" },
  { "carName": "Nissan" },
  { "carName": "Lexus" },
  { "carName": "Toyota" },
  { "carName": "Ford" },
  { "carName": "Lamborghini" },
  { "carName": "Dodge" },
  { "carName": "Chevrolet" },
  { "carName": "Volkswagen" },
  { "carName": "Chrysler" },
  { "carName": "Audi" },
  { "carName": "Audi" },
  { "carName": "Mazda" },
  { "carName": "Hyundai" },
  { "carName": "Acura" },
  { "carName": "Mazda" },
  { "carName": "Toyota" },
  { "carName": "Chevrolet" },
  { "carName": "Acura" },
  { "carName": "Subaru" },
  { "carName": "Ford" },
  { "carName": "Ferrari" },
  { "carName": "Volkswagen" },
  { "carName": "GMC" },
  { "carName": "Land Rover" },
  { "carName": "BMW" },
  { "carName": "Audi" },
  { "carName": "Buick" },
  { "carName": "Mercedes-Benz" },
  { "carName": "Honda" },
  { "carName": "Acura" },
  { "carName": "Lexus" },
  { "carName": "Toyota" },
  { "carName": "Ford" },
  { "carName": "Chevrolet" },
  { "carName": "Mercedes-Benz" },
  { "carName": "Toyota" },
  { "carName": "Honda" },
  { "carName": "Mercedes-Benz" },
  { "carName": "Pontiac" },
  { "carName": "Chevrolet" },
  { "carName": "Lexus" },
  { "carName": "Lexus" },
  { "carName": "BMW" },
  { "carName": "Mitsubishi" },
  { "carName": "Suzuki" },
  { "carName": "Mazda" },
  { "carName": "Audi" },
  { "carName": "Ford" },
  { "carName": "Porsche" },
  { "carName": "Mercury" },
  { "carName": "Lexus" },
  { "carName": "Daewoo" },
  { "carName": "Pontiac" },
  { "carName": "Kia" },
  { "carName": "Jaguar" },
  { "carName": "Audi" },
  { "carName": "Land Rover" },
  { "carName": "Maserati" },
  { "carName": "Toyota" },
  { "carName": "Toyota" },
  { "carName": "Bentley" },
  { "carName": "Audi" },
  { "carName": "Dodge" },
  { "carName": "Suzuki" },
  { "carName": "Ford" },
  { "carName": "Toyota" },
  { "carName": "GMC" },
  { "carName": "Ford" },
  { "carName": "Nissan" },
  { "carName": "Lexus" },
  { "carName": "Pontiac" },
  { "carName": "Chevrolet" },
  { "carName": "Lexus" },
  { "carName": "Volkswagen" },
  { "carName": "Mercury" },
  { "carName": "Porsche" },
  { "carName": "Pontiac" },
  { "carName": "Buick" },
  { "carName": "Lotus" },
  { "carName": "Buick" },
  { "carName": "Chevrolet" },
  { "carName": "Volvo" },
  { "carName": "Volkswagen" },
  { "carName": "Mazda" },
  { "carName": "Chevrolet" },
  { "carName": "Oldsmobile" },
  { "carName": "Morgan" },
  { "carName": "Ford" },
  { "carName": "Chevrolet" },
  { "carName": "Chevrolet" },
  { "carName": "Subaru" },
  { "carName": "Studebaker" },
  { "carName": "Acura" },
  { "carName": "Honda" },
  { "carName": "Saturn" },
  { "carName": "Hyundai" },
  { "carName": "Mercury" },
  { "carName": "Kia" },
  { "carName": "Nissan" },
  { "carName": "Ford" },
  { "carName": "Isuzu" },
  { "carName": "Chevrolet" },
  { "carName": "Ford" },
  { "carName": "Pontiac" },
  { "carName": "Ford" },
  { "carName": "Citroën" },
  { "carName": "Chevrolet" },
  { "carName": "Toyota" },
  { "carName": "Jaguar" },
  { "carName": "Audi" },
  { "carName": "Land Rover" },
  { "carName": "Land Rover" },
  { "carName": "BMW" },
  { "carName": "BMW" },
  { "carName": "Pontiac" },
  { "carName": "Mercedes-Benz" },
  { "carName": "Kia" },
  { "carName": "Lexus" },
  { "carName": "Toyota" },
  { "carName": "Isuzu" },
  { "carName": "Chevrolet" },
  { "carName": "GMC" },
  { "carName": "Jaguar" },
  { "carName": "Mitsubishi" },
  { "carName": "Mazda" },
  { "carName": "Toyota" },
  { "carName": "Chevrolet" },
  { "carName": "Ford" },
  { "carName": "BMW" },
  { "carName": "Lincoln" },
  { "carName": "Volkswagen" },
  { "carName": "Ford" },
  { "carName": "Saab" },
  { "carName": "Maserati" },
  { "carName": "Mazda" },
  { "carName": "Porsche" },
  { "carName": "Mercedes-Benz" },
  { "carName": "Nissan" },
  { "carName": "Holden" },
  { "carName": "Audi" },
  { "carName": "Isuzu" },
  { "carName": "Mercedes-Benz" },
  { "carName": "Buick" },
  { "carName": "Mercedes-Benz" },
  { "carName": "Mazda" },
  { "carName": "Toyota" },
  { "carName": "Volkswagen" },
  { "carName": "Mitsubishi" },
  { "carName": "Mercury" },
  { "carName": "Mazda" },
  { "carName": "Ford" },
  { "carName": "Toyota" },
  { "carName": "Ford" },
  { "carName": "Infiniti" },
  { "carName": "Mercedes-Benz" },
  { "carName": "Hyundai" },
  { "carName": "Pontiac" },
  { "carName": "Mercedes-Benz" },
  { "carName": "Nissan" },
  { "carName": "Toyota" },
  { "carName": "Plymouth" },
  { "carName": "Chevrolet" },
  { "carName": "Ford" },
  { "carName": "Nissan" },
  { "carName": "Oldsmobile" },
  { "carName": "GMC" },
  { "carName": "Eagle" },
  { "carName": "Cadillac" },
  { "carName": "Audi" },
  { "carName": "Porsche" },
  { "carName": "Toyota" },
  { "carName": "Chrysler" },
  { "carName": "Pontiac" },
  { "carName": "Mazda" },
  { "carName": "Mazda" },
  { "carName": "Buick" },
  { "carName": "Nissan" },
  { "carName": "Chevrolet" },
  { "carName": "GMC" },
  { "carName": "Cadillac" },
  { "carName": "Mercury" },
  { "carName": "Buick" },
  { "carName": "Buick" },
  { "carName": "BMW" },
  { "carName": "Ford" },
  { "carName": "Ford" },
  { "carName": "BMW" },
  { "carName": "Chevrolet" },
  { "carName": "GMC" },
  { "carName": "Mercedes-Benz" },
  { "carName": "Oldsmobile" },
  { "carName": "Suzuki" },
  { "carName": "Infiniti" },
  { "carName": "Lincoln" },
  { "carName": "Plymouth" },
  { "carName": "Chrysler" },
  { "carName": "Porsche" },
  { "carName": "Chevrolet" },
  { "carName": "Mazda" },
  { "carName": "Lexus" },
  { "carName": "Mitsubishi" },
  { "carName": "GMC" },
  { "carName": "GMC" },
  { "carName": "Dodge" },
  { "carName": "Subaru" },
  { "carName": "Mitsubishi" },
  { "carName": "Lincoln" },
  { "carName": "Honda" },
  { "carName": "Ford" },
  { "carName": "Lexus" },
  { "carName": "Buick" },
  { "carName": "Toyota" },
  { "carName": "Audi" },
  { "carName": "Lotus" },
  { "carName": "Ford" },
  { "carName": "Toyota" },
  { "carName": "Bentley" },
  { "carName": "Mercedes-Benz" },
  { "carName": "Mitsubishi" },
  { "carName": "Dodge" },
  { "carName": "Acura" },
  { "carName": "Honda" },
  { "carName": "Buick" },
  { "carName": "Pontiac" },
  { "carName": "Mercedes-Benz" },
  { "carName": "Buick" },
  { "carName": "Ram" },
  { "carName": "Chevrolet" },
  { "carName": "Volvo" },
  { "carName": "Chrysler" },
  { "carName": "Chevrolet" },
  { "carName": "Honda" },
  { "carName": "Honda" },
  { "carName": "Jeep" },
  { "carName": "Porsche" },
  { "carName": "Infiniti" },
  { "carName": "Chevrolet" },
  { "carName": "Ford" },
  { "carName": "Subaru" },
  { "carName": "Honda" },
  { "carName": "Hummer" },
  { "carName": "Chevrolet" },
  { "carName": "Mazda" },
  { "carName": "Toyota" },
  { "carName": "Mazda" },
  { "carName": "Mazda" },
  { "carName": "Subaru" },
  { "carName": "Chevrolet" },
  { "carName": "Nissan" },
  { "carName": "Ford" },
  { "carName": "Mazda" },
  { "carName": "Lotus" },
  { "carName": "Dodge" },
  { "carName": "Cadillac" },
  { "carName": "Ford" },
  { "carName": "Toyota" },
  { "carName": "Kia" },
  { "carName": "Mazda" },
  { "carName": "Saab" },
  { "carName": "Mitsubishi" },
  { "carName": "Ford" },
  { "carName": "Isuzu" },
  { "carName": "Ford" },
  { "carName": "GMC" },
  { "carName": "Mercedes-Benz" },
  { "carName": "Chevrolet" },
  { "carName": "Lincoln" },
  { "carName": "Hyundai" },
  { "carName": "Subaru" },
  { "carName": "Aston Martin" },
  { "carName": "Lincoln" },
  { "carName": "Aptera" },
  { "carName": "Maserati" },
  { "carName": "Mercury" },
  { "carName": "BMW" },
  { "carName": "Chrysler" },
  { "carName": "Mazda" },
  { "carName": "Mercury" },
  { "carName": "Chevrolet" },
  { "carName": "Plymouth" },
  { "carName": "Mazda" },
  { "carName": "Mitsubishi" },
  { "carName": "Maybach" },
  { "carName": "Porsche" },
  { "carName": "Dodge" },
  { "carName": "Dodge" },
  { "carName": "Oldsmobile" },
  { "carName": "Volvo" },
  { "carName": "Chevrolet" },
  { "carName": "Toyota" },
  { "carName": "Mercedes-Benz" },
  { "carName": "Subaru" },
  { "carName": "Land Rover" },
  { "carName": "Chevrolet" },
  { "carName": "Saab" },
  { "carName": "Audi" },
  { "carName": "Honda" },
  { "carName": "Honda" },
  { "carName": "Kia" },
  { "carName": "Pontiac" },
  { "carName": "Ford" },
  { "carName": "Oldsmobile" },
  { "carName": "Corbin" },
  { "carName": "Toyota" },
  { "carName": "Mitsubishi" },
  { "carName": "Land Rover" },
  { "carName": "Ford" },
  { "carName": "Buick" },
  { "carName": "Mitsubishi" },
  { "carName": "Volvo" },
  { "carName": "Cadillac" },
  { "carName": "Honda" },
  { "carName": "GMC" },
  { "carName": "Oldsmobile" },
  { "carName": "Toyota" },
  { "carName": "GMC" },
  { "carName": "Toyota" },
  { "carName": "Dodge" },
  { "carName": "Lexus" },
  { "carName": "Toyota" },
  { "carName": "Kia" },
  { "carName": "Ford" },
  { "carName": "Mercedes-Benz" },
  { "carName": "Hyundai" },
  { "carName": "Chevrolet" },
  { "carName": "Dodge" },
  { "carName": "Infiniti" },
  { "carName": "Chevrolet" },
  { "carName": "Volkswagen" },
  { "carName": "Acura" },
  { "carName": "Chevrolet" },
  { "carName": "Lexus" },
  { "carName": "Saturn" },
  { "carName": "Suzuki" },
  { "carName": "Toyota" },
  { "carName": "Audi" },
  { "carName": "Suzuki" },
  { "carName": "Mazda" },
  { "carName": "Mitsubishi" },
  { "carName": "Dodge" },
  { "carName": "BMW" },
  { "carName": "Chrysler" },
  { "carName": "Chevrolet" },
  { "carName": "BMW" },
  { "carName": "Chevrolet" },
  { "carName": "Mercury" },
  { "carName": "Suzuki" },
  { "carName": "Lamborghini" },
  { "carName": "Dodge" },
  { "carName": "Lincoln" },
  { "carName": "Audi" },
  { "carName": "Toyota" },
  { "carName": "Acura" },
  { "carName": "Geo" },
  { "carName": "Hyundai" },
  { "carName": "Chevrolet" },
  { "carName": "Lamborghini" },
  { "carName": "Porsche" },
  { "carName": "Kia" },
  { "carName": "Mercury" },
  { "carName": "Porsche" },
  { "carName": "Dodge" },
  { "carName": "Land Rover" },
  { "carName": "Lexus" },
  { "carName": "Ford" },
  { "carName": "Toyota" },
  { "carName": "Jensen" },
  { "carName": "Lincoln" },
  { "carName": "Chevrolet" },
  { "carName": "Porsche" },
  { "carName": "Kia" },
  { "carName": "Ford" },
  { "carName": "Mercury" },
  { "carName": "Chevrolet" },
  { "carName": "Pontiac" },
  { "carName": "GMC" },
  { "carName": "GMC" },
  { "carName": "Mazda" },
  { "carName": "Lincoln" },
  { "carName": "Chevrolet" },
  { "carName": "Ford" },
  { "carName": "Chevrolet" },
  { "carName": "Cadillac" },
  { "carName": "Audi" },
  { "carName": "Buick" },
  { "carName": "Plymouth" },
  { "carName": "Cadillac" },
  { "carName": "Infiniti" },
  { "carName": "Suzuki" },
  { "carName": "Acura" },
  { "carName": "Nissan" },
  { "carName": "Lotus" },
  { "carName": "Ferrari" },
  { "carName": "Subaru" },
  { "carName": "Chrysler" },
  { "carName": "Dodge" },
  { "carName": "Pontiac" },
  { "carName": "Cadillac" },
  { "carName": "Honda" },
  { "carName": "Mazda" },
  { "carName": "Chevrolet" },
  { "carName": "Hummer" },
  { "carName": "Mazda" },
  { "carName": "Toyota" },
  { "carName": "Infiniti" },
  { "carName": "GMC" },
  { "carName": "Chevrolet" },
  { "carName": "Fillmore" },
  { "carName": "Volvo" },
  { "carName": "Saab" },
  { "carName": "Porsche" },
  { "carName": "Subaru" },
  { "carName": "Mitsubishi" },
  { "carName": "Ford" },
  { "carName": "Toyota" },
  { "carName": "Mazda" },
  { "carName": "Mitsubishi" },
  { "carName": "Chevrolet" },
  { "carName": "Ford" },
  { "carName": "Toyota" },
  { "carName": "GMC" },
  { "carName": "Chevrolet" },
  { "carName": "Ford" },
  { "carName": "Mitsubishi" },
  { "carName": "Audi" },
  { "carName": "Lamborghini" },
  { "carName": "Cadillac" },
  { "carName": "Ford" },
  { "carName": "Honda" },
  { "carName": "Bentley" },
  { "carName": "GMC" },
  { "carName": "Hyundai" },
  { "carName": "Nissan" },
  { "carName": "Audi" },
  { "carName": "BMW" },
  { "carName": "Saab" }
]
